sqlite_worker/__init__.py
sqlite_worker/main.py
sqlite_worker-0.0.4.dist-info/LICENSE
sqlite_worker-0.0.4.dist-info/METADATA
sqlite_worker-0.0.4.dist-info/WHEEL
sqlite_worker-0.0.4.dist-info/top_level.txt
sqlite_worker-0.0.4.dist-info/RECORD
